timm-vis/__init__.py
timm-vis/helpers.py
timm-vis/methods.py
timm-vis/visualizer.py
timm_vis/__init__.py
timm_vis/helpers.py
timm_vis/methods.py
timm_vis/visualizer.py
timm_vis-2.0.0.dist-info/LICENSE
timm_vis-2.0.0.dist-info/METADATA
timm_vis-2.0.0.dist-info/WHEEL
timm_vis-2.0.0.dist-info/top_level.txt
timm_vis-2.0.0.dist-info/RECORD
