Metadata-Version: 2.1
Name: timm-vis
Version: 2.0.0
Summary: Visualizer for PyTorch image models
Home-page: https://github.com/novice03/timm-vis
Author: Pranav Pulijala
License: UNKNOWN
Platform: UNKNOWN
Classifier: Programming Language :: Python :: 3
Classifier: Operating System :: OS Independent
License-File: LICENSE
